{
    "no": "202604090088",
    "endDate": "2026-04-08T16:00:00.000+0000",
    "actualEndTime": "2026-04-09T08:40:01.370+0000",
    "waterOffArea": {
        "type": "MultiPolygon",
        "coordinates": [
            [
                [
                    [
                        120.2459406853377,
                        22.883763681885934
                    ],
                    [
                        120.2455973625838,
                        22.883459241150216
                    ],
                    [
                        120.24556303017742,
                        22.882664528790727
                    ],
                    [
                        120.24502229697103,
                        22.882205886817374
                    ],
                    [
                        120.24481630338414,
                        22.88137558264232
                    ],
                    [
                        120.24515962613803,
                        22.880225009801123
                    ],
                    [
                        120.24606943137042,
                        22.880984151709633
                    ],
                    [
                        120.24622315888125,
                        22.881013502692838
                    ],
                    [
                        120.24619307196325,
                        22.88112834116652
                    ],
                    [
                        120.24610281055332,
                        22.881365937575186
                    ],
                    [
                        120.24600395330275,
                        22.881789650168876
                    ],
                    [
                        120.24647674979003,
                        22.881991606098573
                    ],
                    [
                        120.24726247787474,
                        22.88236008557489
                    ],
                    [
                        120.24757146854974,
                        22.8819172577863
                    ],
                    [
                        120.24782037734987,
                        22.881648397401253
                    ],
                    [
                        120.24814733459216,
                        22.881075041373904
                    ],
                    [
                        120.2487000458225,
                        22.88134556445421
                    ],
                    [
                        120.24852300553023,
                        22.88156039153109
                    ],
                    [
                        120.24819051490381,
                        22.881958218160143
                    ],
                    [
                        120.24790984116524,
                        22.882232717763404
                    ],
                    [
                        120.24779462827424,
                        22.882435207967564
                    ],
                    [
                        120.24737834923869,
                        22.882905710678138
                    ],
                    [
                        120.24696207046509,
                        22.88333667382945
                    ],
                    [
                        120.24637413037998,
                        22.883751820629925
                    ],
                    [
                        120.2459406853377,
                        22.883763681885934
                    ]
                ]
            ]
        ]
    },
    "startTime": "15:27:00",
    "lastUpdatedTime": "2026-04-09T08:40:01.370+0000",
    "endTime": "19:30:00",
    "category": 1,
    "type": 1,
    "startDate": "2026-04-08T16:00:00.000+0000",
    "pressureDownArea": null,
    "isSchedule": false
}