{
    "no": "202605060051",
    "endDate": "2026-05-05T16:00:00.000+0000",
    "actualEndTime": null,
    "waterOffArea": null,
    "startTime": "10:53:00",
    "lastUpdatedTime": "2026-05-06T02:53:01.886+0000",
    "endTime": "16:00:00",
    "category": 1,
    "type": 1,
    "startDate": "2026-05-05T16:00:00.000+0000",
    "pressureDownArea": {
        "type": "MultiPolygon",
        "coordinates": [
            [
                [
                    [
                        120.66189765930176,
                        24.13004085258406
                    ],
                    [
                        120.66174745559694,
                        24.132292843241792
                    ],
                    [
                        120.66164016723634,
                        24.140164707681585
                    ],
                    [
                        120.66563129425049,
                        24.14010596421937
                    ],
                    [
                        120.6667470932007,
                        24.141163342409246
                    ],
                    [
                        120.6728410720825,
                        24.13589594581417
                    ],
                    [
                        120.67043781280518,
                        24.13364401860302
                    ],
                    [
                        120.66876411437987,
                        24.132057854765222
                    ],
                    [
                        120.663743019104,
                        24.130021269882693
                    ],
                    [
                        120.66189765930176,
                        24.13004085258406
                    ]
                ]
            ]
        ]
    },
    "isSchedule": false
}