{
    "no": "202602120018",
    "endDate": "2026-02-11T16:00:00.000+0000",
    "actualEndTime": null,
    "waterOffArea": {
        "type": "MultiPolygon",
        "coordinates": [
            [
                [
                    [
                        120.20509600639342,
                        23.012326763902042
                    ],
                    [
                        120.20484924316409,
                        23.009660475798295
                    ],
                    [
                        120.2052354812622,
                        23.009709851982805
                    ],
                    [
                        120.20607233047487,
                        23.009423469861133
                    ],
                    [
                        120.20641565322876,
                        23.009393844089708
                    ],
                    [
                        120.20748853683473,
                        23.009087710737457
                    ],
                    [
                        120.20814299583435,
                        23.01011473601413
                    ],
                    [
                        120.20862579345703,
                        23.01150713279837
                    ],
                    [
                        120.20639419555663,
                        23.01215888805743
                    ],
                    [
                        120.20509600639342,
                        23.012326763902042
                    ]
                ]
            ]
        ]
    },
    "startTime": "10:19:00",
    "lastUpdatedTime": "2026-02-12T02:19:36.433+0000",
    "endTime": "13:30:00",
    "category": 2,
    "type": 1,
    "startDate": "2026-02-11T16:00:00.000+0000",
    "pressureDownArea": {
        "type": "MultiPolygon",
        "coordinates": [
            [
                [
                    [
                        120.20507454872131,
                        23.012316888858145
                    ],
                    [
                        120.20482778549193,
                        23.009660475798295
                    ],
                    [
                        120.19992470741272,
                        23.009581473865502
                    ],
                    [
                        120.20051479339601,
                        23.01071712220226
                    ],
                    [
                        120.20066499710082,
                        23.011734259988533
                    ],
                    [
                        120.20232796669005,
                        23.01224776353061
                    ],
                    [
                        120.20366907119751,
                        23.012435389337238
                    ],
                    [
                        120.20507454872131,
                        23.012316888858145
                    ]
                ]
            ]
        ]
    },
    "isSchedule": false
}