{
    "no": "202604210052",
    "endDate": "2026-04-20T16:00:00.000+0000",
    "actualEndTime": null,
    "waterOffArea": {
        "type": "MultiPolygon",
        "coordinates": [
            [
                [
                    [
                        120.65513044595718,
                        23.94067475131306
                    ],
                    [
                        120.65432897811401,
                        23.939590699972957
                    ],
                    [
                        120.65543376596739,
                        23.938037725090666
                    ],
                    [
                        120.6567413313382,
                        23.93877267438061
                    ],
                    [
                        120.65513044595718,
                        23.94067475131306
                    ]
                ]
            ]
        ]
    },
    "startTime": "13:00:00",
    "lastUpdatedTime": "2026-04-21T03:28:11.745+0000",
    "endTime": "17:00:00",
    "category": 1,
    "type": 1,
    "startDate": "2026-04-20T16:00:00.000+0000",
    "pressureDownArea": null,
    "isSchedule": false
}