{
    "no": "202602030027",
    "endDate": "2026-02-02T16:00:00.000+0000",
    "actualEndTime": null,
    "waterOffArea": null,
    "startTime": "10:00:00",
    "lastUpdatedTime": "2026-02-03T01:54:33.409+0000",
    "endTime": "14:00:00",
    "category": 1,
    "type": 1,
    "startDate": "2026-02-02T16:00:00.000+0000",
    "pressureDownArea": {
        "type": "MultiPolygon",
        "coordinates": [
            [
                [
                    [
                        120.55334921100346,
                        24.280053390312197
                    ],
                    [
                        120.56039839153708,
                        24.277384996070968
                    ],
                    [
                        120.56139751439511,
                        24.277177170088507
                    ],
                    [
                        120.56268497472226,
                        24.27716494502012
                    ],
                    [
                        120.56411325096778,
                        24.277152719963045
                    ],
                    [
                        120.5645826375454,
                        24.275606239176472
                    ],
                    [
                        120.56496485233002,
                        24.274261457972464
                    ],
                    [
                        120.56537388917796,
                        24.27267215278307
                    ],
                    [
                        120.56562869903436,
                        24.271877492713347
                    ],
                    [
                        120.5663394844233,
                        24.271107278979816
                    ],
                    [
                        120.56708212097018,
                        24.270430587388375
                    ],
                    [
                        120.5532201296992,
                        24.275414914362067
                    ],
                    [
                        120.55334921100346,
                        24.280053390312197
                    ]
                ]
            ],
            [
                [
                    [
                        120.55334418190971,
                        24.280062253270795
                    ],
                    [
                        120.55185723227626,
                        24.28067074073899
                    ],
                    [
                        120.5506720311678,
                        24.281153616717653
                    ],
                    [
                        120.54979193136137,
                        24.281402694422642
                    ],
                    [
                        120.54915323033971,
                        24.281407278670475
                    ],
                    [
                        120.54901241436643,
                        24.280869392462158
                    ],
                    [
                        120.55040045753616,
                        24.280433275118448
                    ],
                    [
                        120.550011537229,
                        24.279470572059854
                    ],
                    [
                        120.55235176453824,
                        24.27787399700754
                    ],
                    [
                        120.55144651899572,
                        24.276547577503138
                    ],
                    [
                        120.55171473989579,
                        24.275985220377752
                    ],
                    [
                        120.55323689351172,
                        24.275404522881853
                    ],
                    [
                        120.55334418190971,
                        24.280062253270795
                    ]
                ]
            ]
        ]
    },
    "isSchedule": false
}