{
    "no": "202506280011",
    "endDate": "2025-06-27T16:00:00.000+0000",
    "actualEndTime": null,
    "waterOffArea": null,
    "startTime": "09:09:00",
    "lastUpdatedTime": "2025-06-28T01:11:54.803+0000",
    "endTime": "17:00:00",
    "category": 2,
    "type": 1,
    "startDate": "2025-06-27T16:00:00.000+0000",
    "pressureDownArea": {
        "type": "MultiPolygon",
        "coordinates": [
            [
                [
                    [
                        120.85852637650133,
                        24.260287625432753
                    ],
                    [
                        120.8581859801686,
                        24.2586389582058
                    ],
                    [
                        120.86014067317761,
                        24.2582389800772
                    ],
                    [
                        120.86207706449453,
                        24.25846315939984
                    ],
                    [
                        120.86404419218155,
                        24.257930732863144
                    ],
                    [
                        120.86639040176661,
                        24.257407644971636
                    ],
                    [
                        120.86743543835036,
                        24.25782798362572
                    ],
                    [
                        120.8695255115178,
                        24.258444477804716
                    ],
                    [
                        120.87244546667827,
                        24.258416455406884
                    ],
                    [
                        120.87576499465014,
                        24.257127418430244
                    ],
                    [
                        120.8781624315187,
                        24.258108208623106
                    ],
                    [
                        120.88111312304926,
                        24.259789545637297
                    ],
                    [
                        120.87988366824487,
                        24.261825801804687
                    ],
                    [
                        120.87810095877849,
                        24.262442276597604
                    ],
                    [
                        120.87335731232486,
                        24.26275051287294
                    ],
                    [
                        120.86955624788794,
                        24.263161493410742
                    ],
                    [
                        120.8642388558589,
                        24.26187250454517
                    ],
                    [
                        120.86177994625011,
                        24.261059874412553
                    ],
                    [
                        120.85852637650133,
                        24.260287625432753
                    ]
                ]
            ]
        ]
    },
    "isSchedule": false
}