{
    "no": "202509170007",
    "endDate": "2025-09-16T16:00:00.000+0000",
    "actualEndTime": null,
    "waterOffArea": {
        "type": "MultiPolygon",
        "coordinates": [
            [
                [
                    [
                        120.36408662796019,
                        23.07657329256602
                    ],
                    [
                        120.365309715271,
                        23.07763928444565
                    ],
                    [
                        120.36217689514159,
                        23.08362052658396
                    ],
                    [
                        120.35895824432372,
                        23.084311411997806
                    ],
                    [
                        120.35782098770142,
                        23.079356698033003
                    ],
                    [
                        120.36093235015868,
                        23.076356145036048
                    ],
                    [
                        120.36408662796019,
                        23.07657329256602
                    ]
                ]
            ]
        ]
    },
    "startTime": "08:08:00",
    "lastUpdatedTime": "2025-09-17T00:08:36.706+0000",
    "endTime": "12:00:00",
    "category": 2,
    "type": 1,
    "startDate": "2025-09-16T16:00:00.000+0000",
    "pressureDownArea": null,
    "isSchedule": false
}