{
    "no": "202511180046",
    "endDate": "2025-11-17T16:00:00.000+0000",
    "actualEndTime": null,
    "waterOffArea": {
        "type": "MultiPolygon",
        "coordinates": [
            [
                [
                    [
                        120.29242873191833,
                        23.07807542567806
                    ],
                    [
                        120.2924367785454,
                        23.077884189951142
                    ],
                    [
                        120.29387444257736,
                        23.078033477219304
                    ],
                    [
                        120.29393613338469,
                        23.078200037198926
                    ],
                    [
                        120.29348552227019,
                        23.07813958211907
                    ],
                    [
                        120.29344394803046,
                        23.07827776511881
                    ],
                    [
                        120.29338359832762,
                        23.078271596237922
                    ],
                    [
                        120.29337286949156,
                        23.078108737680083
                    ],
                    [
                        120.29242873191833,
                        23.07807542567806
                    ]
                ]
            ]
        ]
    },
    "startTime": "11:40:00",
    "lastUpdatedTime": "2025-11-18T03:40:25.530+0000",
    "endTime": "15:00:00",
    "category": 2,
    "type": 1,
    "startDate": "2025-11-17T16:00:00.000+0000",
    "pressureDownArea": null,
    "isSchedule": false
}