{
    "no": "202508290026",
    "endDate": "2025-08-28T16:00:00.000+0000",
    "actualEndTime": null,
    "waterOffArea": {
        "type": "MultiPolygon",
        "coordinates": [
            [
                [
                    [
                        120.72377933513334,
                        24.298509994360344
                    ],
                    [
                        120.72390300114303,
                        24.294740394106544
                    ],
                    [
                        120.72365566912364,
                        24.290569906785517
                    ],
                    [
                        120.71471051719764,
                        24.29033194813269
                    ],
                    [
                        120.70928296732065,
                        24.293375294811455
                    ],
                    [
                        120.70940996145744,
                        24.295958236633332
                    ],
                    [
                        120.71302041933716,
                        24.299223826521796
                    ],
                    [
                        120.71956096128335,
                        24.29861018251467
                    ],
                    [
                        120.72377933513334,
                        24.298509994360344
                    ]
                ]
            ]
        ]
    },
    "startTime": "10:00:00",
    "lastUpdatedTime": "2025-08-29T01:31:58.647+0000",
    "endTime": "17:00:00",
    "category": 1,
    "type": 1,
    "startDate": "2025-08-28T16:00:00.000+0000",
    "pressureDownArea": null,
    "isSchedule": false
}