{
    "no": "202511040016",
    "endDate": "2025-11-03T16:00:00.000+0000",
    "actualEndTime": null,
    "waterOffArea": {
        "type": "MultiPolygon",
        "coordinates": [
            [
                [
                    [
                        120.29272377490996,
                        22.67887147001269
                    ],
                    [
                        120.29374837875366,
                        22.678544793184127
                    ],
                    [
                        120.29355525970459,
                        22.678252763239104
                    ],
                    [
                        120.29353916645051,
                        22.67798053137427
                    ],
                    [
                        120.29333531856538,
                        22.677807292633428
                    ],
                    [
                        120.29363572597504,
                        22.67723807808676
                    ],
                    [
                        120.29270768165588,
                        22.676569866690855
                    ],
                    [
                        120.2925628423691,
                        22.676946045358754
                    ],
                    [
                        120.29261648654938,
                        22.677233128384696
                    ],
                    [
                        120.29243946075441,
                        22.678005279747964
                    ],
                    [
                        120.29259502887727,
                        22.678569541455953
                    ],
                    [
                        120.29272377490996,
                        22.67887147001269
                    ]
                ]
            ]
        ]
    },
    "startTime": "09:22:00",
    "lastUpdatedTime": "2025-11-04T01:22:48.043+0000",
    "endTime": "11:00:00",
    "category": 1,
    "type": 1,
    "startDate": "2025-11-03T16:00:00.000+0000",
    "pressureDownArea": null,
    "isSchedule": false
}