{
    "no": "202509250050",
    "endDate": "2025-09-24T16:00:00.000+0000",
    "actualEndTime": null,
    "waterOffArea": {
        "type": "MultiPolygon",
        "coordinates": [
            [
                [
                    [
                        121.65695965290068,
                        25.063600417999936
                    ],
                    [
                        121.6562247276306,
                        25.06527200382617
                    ],
                    [
                        121.6518849134445,
                        25.063751056029812
                    ],
                    [
                        121.65270030498502,
                        25.061991981037743
                    ],
                    [
                        121.65695965290068,
                        25.063600417999936
                    ]
                ]
            ]
        ]
    },
    "startTime": "12:30:00",
    "lastUpdatedTime": "2025-09-25T02:53:27.918+0000",
    "endTime": "15:00:00",
    "category": 1,
    "type": 1,
    "startDate": "2025-09-24T16:00:00.000+0000",
    "pressureDownArea": null,
    "isSchedule": false
}