{
    "no": "202504060001",
    "endDate": "2025-04-05T16:00:00.000+0000",
    "actualEndTime": null,
    "waterOffArea": {
        "type": "MultiPolygon",
        "coordinates": [
            [
                [
                    [
                        121.22261345386504,
                        24.951508495217613
                    ],
                    [
                        121.22284412384033,
                        24.951693316850154
                    ],
                    [
                        121.22430860996248,
                        24.95228182599005
                    ],
                    [
                        121.22538685798648,
                        24.95265633034193
                    ],
                    [
                        121.22600913047792,
                        24.952894650700095
                    ],
                    [
                        121.22635781764986,
                        24.952150506012526
                    ],
                    [
                        121.2249255180359,
                        24.951644679605327
                    ],
                    [
                        121.22483968734743,
                        24.951839228469378
                    ],
                    [
                        121.2246733903885,
                        24.952111596362666
                    ],
                    [
                        121.22397065162656,
                        24.95181004615936
                    ],
                    [
                        121.22339665889739,
                        24.951771136401923
                    ],
                    [
                        121.22294068336483,
                        24.951518222678875
                    ],
                    [
                        121.22261345386504,
                        24.951508495217613
                    ]
                ]
            ]
        ]
    },
    "startTime": "11:00:00",
    "lastUpdatedTime": "2025-04-06T02:38:07.487+0000",
    "endTime": "17:00:00",
    "category": 2,
    "type": 1,
    "startDate": "2025-04-05T16:00:00.000+0000",
    "pressureDownArea": null,
    "isSchedule": false
}