{
    "no": "202505190030",
    "endDate": "2025-05-18T16:00:00.000+0000",
    "actualEndTime": null,
    "waterOffArea": {
        "type": "MultiPolygon",
        "coordinates": [
            [
                [
                    [
                        120.71442604064941,
                        24.217173724045374
                    ],
                    [
                        120.71459770202637,
                        24.217760802802935
                    ],
                    [
                        120.71624994277954,
                        24.217878218229767
                    ],
                    [
                        120.71751594543456,
                        24.218034771963847
                    ],
                    [
                        120.71715116500853,
                        24.21644965651811
                    ],
                    [
                        120.71674346923827,
                        24.215158066386596
                    ],
                    [
                        120.71603536605835,
                        24.213807753611935
                    ],
                    [
                        120.71590662002565,
                        24.212007314317038
                    ],
                    [
                        120.71491956710815,
                        24.208719489959186
                    ],
                    [
                        120.7147479057312,
                        24.207628422356613
                    ],
                    [
                        120.71549892425539,
                        24.20553432922051
                    ],
                    [
                        120.71549892425539,
                        24.204859123630957
                    ],
                    [
                        120.71538090705873,
                        24.204360056331044
                    ],
                    [
                        120.71503758430481,
                        24.203890344146128
                    ],
                    [
                        120.71446895599365,
                        24.203557630301223
                    ],
                    [
                        120.71370720863342,
                        24.20316620113653
                    ],
                    [
                        120.71290254592896,
                        24.202745413443914
                    ],
                    [
                        120.71221590042114,
                        24.202124015125076
                    ],
                    [
                        120.71208715438843,
                        24.201517292584075
                    ],
                    [
                        120.7117223739624,
                        24.20081270794491
                    ],
                    [
                        120.71174383163451,
                        24.200675704923974
                    ],
                    [
                        120.71140050888062,
                        24.200734420522405
                    ],
                    [
                        120.70966243743896,
                        24.2007931360938
                    ],
                    [
                        120.71028470993042,
                        24.20208487182247
                    ],
                    [
                        120.71079969406128,
                        24.203807165766325
                    ],
                    [
                        120.71107864379883,
                        24.205666434243568
                    ],
                    [
                        120.71285963058472,
                        24.216567073153467
                    ],
                    [
                        120.71442604064941,
                        24.217173724045374
                    ]
                ]
            ]
        ]
    },
    "startTime": "10:22:00",
    "lastUpdatedTime": "2025-05-19T07:12:25.692+0000",
    "endTime": "17:00:00",
    "category": 2,
    "type": 1,
    "startDate": "2025-05-18T16:00:00.000+0000",
    "pressureDownArea": null,
    "isSchedule": false
}