{
    "no": "202505090069",
    "endDate": "2025-05-08T16:00:00.000+0000",
    "actualEndTime": null,
    "waterOffArea": {
        "type": "MultiPolygon",
        "coordinates": [
            [
                [
                    [
                        121.05350875867587,
                        24.701550545016477
                    ],
                    [
                        121.05521678937656,
                        24.703180251705987
                    ],
                    [
                        121.05678749123763,
                        24.702314716496574
                    ],
                    [
                        121.05954265620674,
                        24.701230839208595
                    ],
                    [
                        121.0594310760498,
                        24.7002639194471
                    ],
                    [
                        121.05923366520436,
                        24.699203417801154
                    ],
                    [
                        121.05924224879706,
                        24.698041534387084
                    ],
                    [
                        121.05924224879709,
                        24.69733192271883
                    ],
                    [
                        121.05758571624754,
                        24.697581456798748
                    ],
                    [
                        121.05556011213048,
                        24.697573658977863
                    ],
                    [
                        121.05485630048499,
                        24.697924565550775
                    ],
                    [
                        121.05429840100987,
                        24.698782333594142
                    ],
                    [
                        121.05398941066233,
                        24.699780456484095
                    ],
                    [
                        121.05359458929888,
                        24.700248323724225
                    ],
                    [
                        121.05350875867587,
                        24.701550545016477
                    ]
                ]
            ]
        ]
    },
    "startTime": "14:21:00",
    "lastUpdatedTime": "2025-05-09T06:21:58.348+0000",
    "endTime": "15:30:00",
    "category": 1,
    "type": 1,
    "startDate": "2025-05-08T16:00:00.000+0000",
    "pressureDownArea": null,
    "isSchedule": false
}