{
    "no": "202506250035",
    "endDate": "2025-06-24T16:00:00.000+0000",
    "actualEndTime": null,
    "waterOffArea": {
        "type": "MultiPolygon",
        "coordinates": [
            [
                [
                    [
                        119.56561693166748,
                        23.534680377871656
                    ],
                    [
                        119.56568827657505,
                        23.534616910207916
                    ],
                    [
                        119.56575218890355,
                        23.534460914663878
                    ],
                    [
                        119.56583748548012,
                        23.534295811205343
                    ],
                    [
                        119.5658763785352,
                        23.534157965549902
                    ],
                    [
                        119.56586136817184,
                        23.5340112857289
                    ],
                    [
                        119.56586093569902,
                        23.533909702885968
                    ],
                    [
                        119.56590347345885,
                        23.53383730914057
                    ],
                    [
                        119.56594583843791,
                        23.53372428245808
                    ],
                    [
                        119.56592681845872,
                        23.53349860774707
                    ],
                    [
                        119.56594047039147,
                        23.533326992033512
                    ],
                    [
                        119.56595831246842,
                        23.53327726281686
                    ],
                    [
                        119.56601146187081,
                        23.53318225446198
                    ],
                    [
                        119.56610444485995,
                        23.533098391291094
                    ],
                    [
                        119.56619701426231,
                        23.53298969596876
                    ],
                    [
                        119.56629986547716,
                        23.53278163309533
                    ],
                    [
                        119.56632106790141,
                        23.532659652456754
                    ],
                    [
                        119.56635588902135,
                        23.532431520240703
                    ],
                    [
                        119.56638735977951,
                        23.532277896438682
                    ],
                    [
                        119.56648323910464,
                        23.532085663574822
                    ],
                    [
                        119.56659740973794,
                        23.53194754205579
                    ],
                    [
                        119.56673623101047,
                        23.531777725375434
                    ],
                    [
                        119.56689339986679,
                        23.5316755671205
                    ],
                    [
                        119.56715082967686,
                        23.53154595394149
                    ],
                    [
                        119.56746904371981,
                        23.53138902976392
                    ],
                    [
                        119.56778348645815,
                        23.531209542476304
                    ],
                    [
                        119.56803742956586,
                        23.531122833592054
                    ],
                    [
                        119.56825260081175,
                        23.531128821139674
                    ],
                    [
                        119.56843545978548,
                        23.531164273771164
                    ],
                    [
                        119.56861463670866,
                        23.531197482378317
                    ],
                    [
                        119.56892331364163,
                        23.53131148772126
                    ],
                    [
                        119.56903469005763,
                        23.531306565955695
                    ],
                    [
                        119.56927133234811,
                        23.531323761600333
                    ],
                    [
                        119.56949375840435,
                        23.531379385409814
                    ],
                    [
                        119.56970879124843,
                        23.531423749137687
                    ],
                    [
                        119.56980568557644,
                        23.53146628757954
                    ],
                    [
                        119.56995291425653,
                        23.53154250330553
                    ],
                    [
                        119.5701540076335,
                        23.53161852114626
                    ],
                    [
                        119.57023303073703,
                        23.531704016753032
                    ],
                    [
                        119.57030508591762,
                        23.531735358070474
                    ],
                    [
                        119.57047352351358,
                        23.53176183157653
                    ],
                    [
                        119.570641881793,
                        23.53177024399148
                    ],
                    [
                        119.5707746109253,
                        23.531819423525082
                    ],
                    [
                        119.57106549909723,
                        23.531924458669213
                    ],
                    [
                        119.57121956372318,
                        23.53195324014109
                    ],
                    [
                        119.57131556987831,
                        23.531932571251733
                    ],
                    [
                        119.57157449553539,
                        23.53193613683121
                    ],
                    [
                        119.57167291964514,
                        23.53197866724187
                    ],
                    [
                        119.57188747052629,
                        23.53198239572268
                    ],
                    [
                        119.5719257844863,
                        23.531925818547556
                    ],
                    [
                        119.5719493804329,
                        23.53186252131078
                    ],
                    [
                        119.57196416966124,
                        23.531815060127432
                    ],
                    [
                        119.5720145078719,
                        23.53177875607382
                    ],
                    [
                        119.57207368291269,
                        23.53173338999989
                    ],
                    [
                        119.57207949887366,
                        23.531663386696735
                    ],
                    [
                        119.57206716059862,
                        23.53157087525085
                    ],
                    [
                        119.57206655158011,
                        23.531430914616745
                    ],
                    [
                        119.5720245575299,
                        23.531345284131824
                    ],
                    [
                        119.5719168068592,
                        23.53119894321324
                    ],
                    [
                        119.57185676687983,
                        23.531115637689783
                    ],
                    [
                        119.57181788193397,
                        23.531041283255615
                    ],
                    [
                        119.57183184343909,
                        23.53094416084418
                    ],
                    [
                        119.57187604363735,
                        23.530833381445625
                    ],
                    [
                        119.57197997784098,
                        23.530735929259293
                    ],
                    [
                        119.57202722605336,
                        23.530692864182026
                    ],
                    [
                        119.57203313031309,
                        23.530643177971765
                    ],
                    [
                        119.57204467396706,
                        23.53055283759197
                    ],
                    [
                        119.57207726134135,
                        23.53051659851116
                    ],
                    [
                        119.5721038370955,
                        23.530505212527714
                    ],
                    [
                        119.57225861135645,
                        23.530486584839974
                    ],
                    [
                        119.57230006568832,
                        23.53044805577444
                    ],
                    [
                        119.57229399488081,
                        23.53038938249709
                    ],
                    [
                        119.57241831885204,
                        23.530124802647673
                    ],
                    [
                        119.57284156445955,
                        23.529491155039608
                    ],
                    [
                        119.57350371395029,
                        23.529113978351678
                    ],
                    [
                        119.57347188812679,
                        23.52904411496887
                    ],
                    [
                        119.5728143486338,
                        23.529425788680353
                    ],
                    [
                        119.57234663881057,
                        23.530109262388113
                    ],
                    [
                        119.57228833343225,
                        23.530143338384892
                    ],
                    [
                        119.57205027210944,
                        23.530011022154742
                    ],
                    [
                        119.57273943944384,
                        23.528879754097282
                    ],
                    [
                        119.57265598281423,
                        23.528830396632426
                    ],
                    [
                        119.5722215423754,
                        23.52949343129692
                    ],
                    [
                        119.57122170897064,
                        23.5289981961205
                    ],
                    [
                        119.5718308414001,
                        23.528041050535922
                    ],
                    [
                        119.57226820390855,
                        23.52826067892305
                    ],
                    [
                        119.57203555466181,
                        23.528597896715855
                    ],
                    [
                        119.57218120359163,
                        23.52866282845389
                    ],
                    [
                        119.57236339699838,
                        23.528334826552783
                    ],
                    [
                        119.57252159395969,
                        23.52839971233432
                    ],
                    [
                        119.57261577584677,
                        23.528241342935488
                    ],
                    [
                        119.57193757017846,
                        23.527882635157617
                    ],
                    [
                        119.57200038947622,
                        23.527760501807954
                    ],
                    [
                        119.57208210156753,
                        23.52762023844339
                    ],
                    [
                        119.57214245185178,
                        23.52749359907434
                    ],
                    [
                        119.57227781844996,
                        23.527305731690745
                    ],
                    [
                        119.57234572951731,
                        23.5272287285801
                    ],
                    [
                        119.5726499973208,
                        23.527385634309205
                    ],
                    [
                        119.57318001683502,
                        23.527659098260788
                    ],
                    [
                        119.57333000904026,
                        23.527737559086535
                    ],
                    [
                        119.57277886145607,
                        23.5286561192469
                    ],
                    [
                        119.57289191582761,
                        23.528685051716128
                    ],
                    [
                        119.57348631991384,
                        23.52779116382372
                    ],
                    [
                        119.57354285676965,
                        23.52777289593385
                    ],
                    [
                        119.57361276923926,
                        23.52780424329235
                    ],
                    [
                        119.5737491890476,
                        23.52785792095804
                    ],
                    [
                        119.57381559712664,
                        23.527857676173838
                    ],
                    [
                        119.57387568848357,
                        23.52788228746933
                    ],
                    [
                        119.57389248822811,
                        23.527945434778662
                    ],
                    [
                        119.57402263838144,
                        23.52803525555944
                    ],
                    [
                        119.57428491664258,
                        23.528036546408106
                    ],
                    [
                        119.57440427902986,
                        23.52796838352654
                    ],
                    [
                        119.57446731133233,
                        23.52789591044932
                    ],
                    [
                        119.5744703735986,
                        23.527825918187904
                    ],
                    [
                        119.57444657325655,
                        23.52770184562821
                    ],
                    [
                        119.5743793669538,
                        23.527589218966618
                    ],
                    [
                        119.57429253549311,
                        23.52746763519974
                    ],
                    [
                        119.57421539777042,
                        23.527323440370964
                    ],
                    [
                        119.57419530823327,
                        23.527278365124484
                    ],
                    [
                        119.57418821130008,
                        23.527194865770213
                    ],
                    [
                        119.57417777966089,
                        23.52704816815401
                    ],
                    [
                        119.57415086886988,
                        23.52698280080124
                    ],
                    [
                        119.57412394904804,
                        23.5269151754387
                    ],
                    [
                        119.5740572751834,
                        23.526854468962117
                    ],
                    [
                        119.57397732375311,
                        23.5268367036085
                    ],
                    [
                        119.57389084604023,
                        23.52679638714011
                    ],
                    [
                        119.57365446517333,
                        23.52669792789821
                    ],
                    [
                        119.57353116603204,
                        23.52663517219845
                    ],
                    [
                        119.5733475126073,
                        23.526486853919277
                    ],
                    [
                        119.57320729519621,
                        23.526333860765323
                    ],
                    [
                        119.57306684994573,
                        23.526198928675814
                    ],
                    [
                        119.57301715540349,
                        23.52617202137684
                    ],
                    [
                        119.5727679210349,
                        23.52614358932769
                    ],
                    [
                        119.57260925194574,
                        23.52611031059147
                    ],
                    [
                        119.57247014885684,
                        23.52607244390535
                    ],
                    [
                        119.57234728388141,
                        23.526039032297195
                    ],
                    [
                        119.572152946045,
                        23.52603748856128
                    ],
                    [
                        119.57207757443979,
                        23.52601744618811
                    ],
                    [
                        119.57195474053133,
                        23.525990807605474
                    ],
                    [
                        119.57186747399689,
                        23.525979840226917
                    ],
                    [
                        119.57180791710734,
                        23.52593716680675
                    ],
                    [
                        119.57179564891216,
                        23.52586045740809
                    ],
                    [
                        119.57177544274518,
                        23.52578829199951
                    ],
                    [
                        119.57168785205538,
                        23.525702829270173
                    ],
                    [
                        119.57158453391867,
                        23.52566031567574
                    ],
                    [
                        119.57157611626171,
                        23.525554245149955
                    ],
                    [
                        119.57154004708099,
                        23.525423443400356
                    ],
                    [
                        119.57146831118126,
                        23.525324377655764
                    ],
                    [
                        119.5714599918484,
                        23.52524088123203
                    ],
                    [
                        119.57162908579062,
                        23.52492647270288
                    ],
                    [
                        119.57172729674208,
                        23.524779377945965
                    ],
                    [
                        119.57198328581914,
                        23.52446013760843
                    ],
                    [
                        119.57196706942338,
                        23.524390215469047
                    ],
                    [
                        119.57173665957616,
                        23.524255612445657
                    ],
                    [
                        119.5720052880486,
                        23.52402888121524
                    ],
                    [
                        119.57225414247216,
                        23.523829311907317
                    ],
                    [
                        119.57229750059503,
                        23.523806579039114
                    ],
                    [
                        119.57234523984296,
                        23.5238064032138
                    ],
                    [
                        119.57237681906949,
                        23.523819832345918
                    ],
                    [
                        119.57242072645433,
                        23.523853533548536
                    ],
                    [
                        119.57245622663952,
                        23.52385340367901
                    ],
                    [
                        119.5727329661732,
                        23.523662760442523
                    ],
                    [
                        119.57308055848227,
                        23.52336801327613
                    ],
                    [
                        119.57310399445107,
                        23.523338580316125
                    ],
                    [
                        119.57308380000161,
                        23.523268673144344
                    ],
                    [
                        119.5730994687955,
                        23.52321217911757
                    ],
                    [
                        119.57307701155098,
                        23.52318517200058
                    ],
                    [
                        119.57300611497287,
                        23.523138025687675
                    ],
                    [
                        119.57300900879656,
                        23.523099638643295
                    ],
                    [
                        119.57307776931363,
                        23.522936848645976
                    ],
                    [
                        119.57314080059855,
                        23.52293435885637
                    ],
                    [
                        119.57317214454048,
                        23.5228936099029
                    ],
                    [
                        119.57330146035322,
                        23.52293376840086
                    ],
                    [
                        119.57335442590383,
                        23.522798126373914
                    ],
                    [
                        119.57332588867905,
                        23.522780171251
                    ],
                    [
                        119.57328208578883,
                        23.522841284196197
                    ],
                    [
                        119.5732505756539,
                        23.522843657093738
                    ],
                    [
                        119.57323490951237,
                        23.522830170020857
                    ],
                    [
                        119.57324082429845,
                        23.522782741970197
                    ],
                    [
                        119.57331293914456,
                        23.522687663067945
                    ],
                    [
                        119.57343902973096,
                        23.522689456489182
                    ],
                    [
                        119.57349548679913,
                        23.522653130619663
                    ],
                    [
                        119.57352665351378,
                        23.522571747594455
                    ],
                    [
                        119.57362937635664,
                        23.522266610440962
                    ],
                    [
                        119.5736353418187,
                        23.52216048828909
                    ],
                    [
                        119.57362255947676,
                        23.52210635616178
                    ],
                    [
                        119.57362528608087,
                        23.522029593047073
                    ],
                    [
                        119.573637223759,
                        23.521959567971468
                    ],
                    [
                        119.57360868554505,
                        23.52194161285434
                    ],
                    [
                        119.57356453025524,
                        23.52192145868596
                    ],
                    [
                        119.57356404065817,
                        23.5218085865052
                    ],
                    [
                        119.57348219616078,
                        23.521777283206756
                    ],
                    [
                        119.57346304687132,
                        23.521736719085368
                    ],
                    [
                        119.57345320640832,
                        23.52165548692934
                    ],
                    [
                        119.57355284754382,
                        23.521415828848564
                    ],
                    [
                        119.57363678247431,
                        23.521153654672073
                    ],
                    [
                        119.57368101746864,
                        23.52112188674646
                    ],
                    [
                        119.57393606819397,
                        23.521082571403113
                    ],
                    [
                        119.57393574478424,
                        23.521008076275365
                    ],
                    [
                        119.5738191523639,
                        23.52100850594936
                    ],
                    [
                        119.57379700113762,
                        23.52098149784249
                    ],
                    [
                        119.57378390378605,
                        23.5209251097125
                    ],
                    [
                        119.57379640239122,
                        23.52084379461234
                    ],
                    [
                        119.57380512284786,
                        23.520737661459844
                    ],
                    [
                        119.57378274634426,
                        23.52065873226831
                    ],
                    [
                        119.57379202611978,
                        23.52061129121464
                    ],
                    [
                        119.57385746951832,
                        23.520459800135853
                    ],
                    [
                        119.57396058229425,
                        23.520174980920263
                    ],
                    [
                        119.57397570711774,
                        23.52013429088901
                    ],
                    [
                        119.5740505564111,
                        23.519964705783835
                    ],
                    [
                        119.57413513703413,
                        23.51985152079411
                    ],
                    [
                        119.57421991390189,
                        23.519783484879703
                    ],
                    [
                        119.57431725682494,
                        23.51971991800021
                    ],
                    [
                        119.57441465881897,
                        23.51966989414191
                    ],
                    [
                        119.57451246493987,
                        23.519642443324194
                    ],
                    [
                        119.57457855311372,
                        23.519639943476836
                    ],
                    [
                        119.57460391254277,
                        23.519700801653297
                    ],
                    [
                        119.5746232671152,
                        23.51978877086814
                    ],
                    [
                        119.57467190630841,
                        23.520136241656463
                    ],
                    [
                        119.57485788377802,
                        23.520117496090467
                    ],
                    [
                        119.57498374486613,
                        23.520067367307117
                    ],
                    [
                        119.57506881565824,
                        23.52006705440579
                    ],
                    [
                        119.57529228133444,
                        23.520014307444317
                    ],
                    [
                        119.57543071646589,
                        23.519970903447824
                    ],
                    [
                        119.57562918741755,
                        23.51994082351818
                    ],
                    [
                        119.57579924956651,
                        23.519922134593184
                    ],
                    [
                        119.57590947114872,
                        23.519935271691526
                    ],
                    [
                        119.57592134119713,
                        23.519954858737545
                    ],
                    [
                        119.57592168819846,
                        23.51995543173894
                    ],
                    [
                        119.5759810177623,
                        23.519921461711522
                    ],
                    [
                        119.57603045238466,
                        23.51988967368225
                    ],
                    [
                        119.57605478610833,
                        23.51985572263238
                    ],
                    [
                        119.57608306778266,
                        23.519814983572072
                    ],
                    [
                        119.5761426020266,
                        23.5197131764146
                    ],
                    [
                        119.57616332349728,
                        23.519622801253725
                    ],
                    [
                        119.57615130176033,
                        23.519462565935303
                    ],
                    [
                        119.57613766026972,
                        23.519352000711663
                    ],
                    [
                        119.57612418696502,
                        23.51927981156224
                    ],
                    [
                        119.57605065843812,
                        23.51911980319872
                    ],
                    [
                        119.5759031078144,
                        23.518896860655257
                    ],
                    [
                        119.5757220424088,
                        23.51870790214785
                    ],
                    [
                        119.57548093302256,
                        23.51850336355689
                    ],
                    [
                        119.57516264165268,
                        23.518283307864913
                    ],
                    [
                        119.57490432595186,
                        23.518133010238113
                    ],
                    [
                        119.57462928666584,
                        23.518007606470388
                    ],
                    [
                        119.57436887576908,
                        23.517938584854328
                    ],
                    [
                        119.57400124554725,
                        23.517842868006365
                    ],
                    [
                        119.57400114954093,
                        23.517841756004323
                    ],
                    [
                        119.5740009795451,
                        23.517842580005382
                    ],
                    [
                        119.57399674365126,
                        23.517863203033187
                    ],
                    [
                        119.57392726466237,
                        23.518071147259203
                    ],
                    [
                        119.5739218527027,
                        23.518080458264677
                    ],
                    [
                        119.5738391793125,
                        23.518222720345452
                    ],
                    [
                        119.57383574832255,
                        23.518225840344027
                    ],
                    [
                        119.57376937851164,
                        23.518286187314473
                    ],
                    [
                        119.57375091772853,
                        23.518333661356333
                    ],
                    [
                        119.5737552581871,
                        23.518417171502506
                    ],
                    [
                        119.57372605834277,
                        23.51845791251057
                    ],
                    [
                        119.57370034164965,
                        23.51852573356931
                    ],
                    [
                        119.57370420989972,
                        23.518570868650837
                    ],
                    [
                        119.5737488453268,
                        23.51863165584239
                    ],
                    [
                        119.57373811465428,
                        23.518697160927747
                    ],
                    [
                        119.57370537634044,
                        23.5188395020915
                    ],
                    [
                        119.5736434191416,
                        23.519018069247224
                    ],
                    [
                        119.573628934729,
                        23.519135509404283
                    ],
                    [
                        119.57354512804831,
                        23.519427032679143
                    ],
                    [
                        119.57348318082441,
                        23.519607856818276
                    ],
                    [
                        119.5734095270971,
                        23.5197006837867
                    ],
                    [
                        119.5733213415053,
                        23.51982968277018
                    ],
                    [
                        119.57329195376569,
                        23.51989751580059
                    ],
                    [
                        119.5732846878364,
                        23.519915601809895
                    ],
                    [
                        119.57327411132385,
                        23.520017226936154
                    ],
                    [
                        119.57323404894814,
                        23.52016410805446
                    ],
                    [
                        119.57319128533425,
                        23.520464508388375
                    ],
                    [
                        119.57312989568646,
                        23.52077400767681
                    ],
                    [
                        119.5731042750502,
                        23.52086439973768
                    ],
                    [
                        119.57302415823666,
                        23.52116042193767
                    ],
                    [
                        119.57294374971742,
                        23.521318739929807
                    ],
                    [
                        119.572855671132,
                        23.521472570885425
                    ],
                    [
                        119.57277838232359,
                        23.521574440794996
                    ],
                    [
                        119.57269401476906,
                        23.521737287758928
                    ],
                    [
                        119.57264639103904,
                        23.521834533741742
                    ],
                    [
                        119.57258729709639,
                        23.521897959642896
                    ],
                    [
                        119.57255453126974,
                        23.52196354662584
                    ],
                    [
                        119.57251469470643,
                        23.52209236866554
                    ],
                    [
                        119.57243727971435,
                        23.522164890512837
                    ],
                    [
                        119.57235971755968,
                        23.522203552314945
                    ],
                    [
                        119.5723156186595,
                        23.522266923251532
                    ],
                    [
                        119.57222741083909,
                        23.522391407116714
                    ],
                    [
                        119.57217969797404,
                        23.522468336052103
                    ],
                    [
                        119.57207649775626,
                        23.522522893778266
                    ],
                    [
                        119.57200269568425,
                        23.522581858602404
                    ],
                    [
                        119.5719881827969,
                        23.522622546599642
                    ],
                    [
                        119.57189617479116,
                        23.52271769639843
                    ],
                    [
                        119.57180051477782,
                        23.52281737518437
                    ],
                    [
                        119.5716935116814,
                        23.522912580921354
                    ],
                    [
                        119.57155708138731,
                        23.5229966075407
                    ],
                    [
                        119.5715128052704,
                        23.523019343411402
                    ],
                    [
                        119.57147968333491,
                        23.523073644349555
                    ],
                    [
                        119.57141356028413,
                        23.523139353183126
                    ],
                    [
                        119.57132167833852,
                        23.523263849977237
                    ],
                    [
                        119.57095571165482,
                        23.52355640292782
                    ],
                    [
                        119.57075344216425,
                        23.523701620307538
                    ],
                    [
                        119.57062667296117,
                        23.523826244932646
                    ],
                    [
                        119.57038165350758,
                        23.524064173178633
                    ],
                    [
                        119.56994867637324,
                        23.524431464733325
                    ],
                    [
                        119.5695733560508,
                        23.52468567037812
                    ],
                    [
                        119.56936585126729,
                        23.524824133603108
                    ],
                    [
                        119.5691577782786,
                        23.524901645793882
                    ],
                    [
                        119.56872420926216,
                        23.525061249414886
                    ],
                    [
                        119.56850433115463,
                        23.525168153117832
                    ],
                    [
                        119.56825308770111,
                        23.525311288910043
                    ],
                    [
                        119.56788676270693,
                        23.525592551050625
                    ],
                    [
                        119.56757462833954,
                        23.52573816667588
                    ],
                    [
                        119.5674446135261,
                        23.525819908648373
                    ],
                    [
                        119.56725334567211,
                        23.525820603923847
                    ],
                    [
                        119.56634861661078,
                        23.526009008127545
                    ],
                    [
                        119.56583512515847,
                        23.526085373997713
                    ],
                    [
                        119.56551995144271,
                        23.526093291303095
                    ],
                    [
                        119.56509482669826,
                        23.526081291595823
                    ],
                    [
                        119.56482110145356,
                        23.526120662018045
                    ],
                    [
                        119.56469280397496,
                        23.526175307386172
                    ],
                    [
                        119.56454602436578,
                        23.526272911963833
                    ],
                    [
                        119.56447808758843,
                        23.526273158014494
                    ],
                    [
                        119.56437617187923,
                        23.526271270079892
                    ],
                    [
                        119.56426665340909,
                        23.526280697202875
                    ],
                    [
                        119.56391088414652,
                        23.52631359260413
                    ],
                    [
                        119.56369419975911,
                        23.526309862740952
                    ],
                    [
                        119.56348815806369,
                        23.526290291805676
                    ],
                    [
                        119.56311661193516,
                        23.52621262476825
                    ],
                    [
                        119.56284802288265,
                        23.526093950526523
                    ],
                    [
                        119.56275485353378,
                        23.52599044322006
                    ],
                    [
                        119.56266127082286,
                        23.52586210583428
                    ],
                    [
                        119.56263969117555,
                        23.525753824460637
                    ],
                    [
                        119.56261385351075,
                        23.525580092856856
                    ],
                    [
                        119.56254070341107,
                        23.525363639163047
                    ],
                    [
                        119.56243691751813,
                        23.52521050675292
                    ],
                    [
                        119.56227613471479,
                        23.525039519381018
                    ],
                    [
                        119.56194463171728,
                        23.52466146468387
                    ],
                    [
                        119.561670329314,
                        23.524420907036827
                    ],
                    [
                        119.56138592116471,
                        23.524250366398487
                    ],
                    [
                        119.56121521053943,
                        23.524117792602922
                    ],
                    [
                        119.56095183241514,
                        23.523999096927415
                    ],
                    [
                        119.56057025607655,
                        23.523935005414423
                    ],
                    [
                        119.56033302520308,
                        23.523920058722013
                    ],
                    [
                        119.56003941184431,
                        23.52395949312272
                    ],
                    [
                        119.55978185958462,
                        23.52405974850326
                    ],
                    [
                        119.55963262845584,
                        23.524085116713184
                    ],
                    [
                        119.55943705375415,
                        23.524151287004567
                    ],
                    [
                        119.55929786352051,
                        23.524163074197478
                    ],
                    [
                        119.55900414309323,
                        23.524177675601038
                    ],
                    [
                        119.5587205416398,
                        23.524196753994392
                    ],
                    [
                        119.55862250000995,
                        23.52417001611199
                    ],
                    [
                        119.5585190852015,
                        23.524102663212823
                    ],
                    [
                        119.55836927139288,
                        23.523990328346777
                    ],
                    [
                        119.5582511778128,
                        23.523853046410306
                    ],
                    [
                        119.55811553432311,
                        23.523763235519674
                    ],
                    [
                        119.5580301849741,
                        23.523698075582935
                    ],
                    [
                        119.55792063058828,
                        23.523626229670867
                    ],
                    [
                        119.55772006404248,
                        23.52352536184968
                    ],
                    [
                        119.5575069314805,
                        23.523420025039805
                    ],
                    [
                        119.55724095238229,
                        23.523409690351322
                    ],
                    [
                        119.55709381442428,
                        23.523423763536
                    ],
                    [
                        119.55699390859321,
                        23.52346249767989
                    ],
                    [
                        119.55691584289497,
                        23.523528243814905
                    ],
                    [
                        119.55677258551638,
                        23.523664204073164
                    ],
                    [
                        119.55663237612019,
                        23.523797895327135
                    ],
                    [
                        119.55655176664652,
                        23.52391331549834
                    ],
                    [
                        119.55647737127774,
                        23.524051286676993
                    ],
                    [
                        119.55636832981928,
                        23.524173579888018
                    ],
                    [
                        119.55621902448995,
                        23.524327620169345
                    ],
                    [
                        119.55604443693237,
                        23.52443660245317
                    ],
                    [
                        119.55597588524137,
                        23.5245090875843
                    ],
                    [
                        119.5559383012895,
                        23.524522766639176
                    ],
                    [
                        119.5558385656145,
                        23.52460213381343
                    ],
                    [
                        119.55561779070825,
                        23.524862530256684
                    ],
                    [
                        119.55542494920194,
                        23.525143144723998
                    ],
                    [
                        119.55536921107279,
                        23.525278791921735
                    ],
                    [
                        119.55535449899412,
                        23.525418807073294
                    ],
                    [
                        119.5553705792381,
                        23.525603861230792
                    ],
                    [
                        119.55537146515557,
                        23.525741563361386
                    ],
                    [
                        119.55533437499201,
                        23.525872629529974
                    ],
                    [
                        119.55529126898091,
                        23.5260285487286
                    ],
                    [
                        119.5551920151505,
                        23.526223044026956
                    ],
                    [
                        119.5550522595546,
                        23.526465091412632
                    ],
                    [
                        119.55492191381872,
                        23.526689045766375
                    ],
                    [
                        119.55481002576362,
                        23.526863270050082
                    ],
                    [
                        119.55468874836005,
                        23.52698786229629
                    ],
                    [
                        119.55451777558321,
                        23.527230021698955
                    ],
                    [
                        119.55435282663387,
                        23.527449583069373
                    ],
                    [
                        119.55423124215831,
                        23.52757417630662
                    ],
                    [
                        119.55410362177471,
                        23.527719109565428
                    ],
                    [
                        119.55391366537354,
                        23.527886837904916
                    ],
                    [
                        119.55376735787559,
                        23.52802732117269
                    ],
                    [
                        119.55360223753037,
                        23.528206248488143
                    ],
                    [
                        119.55354315077888,
                        23.528274183603262
                    ],
                    [
                        119.55350932931023,
                        23.528382661726017
                    ],
                    [
                        119.55350086725392,
                        23.528554258875136
                    ],
                    [
                        119.55351700600471,
                        23.528680618963225
                    ],
                    [
                        119.55360511802151,
                        23.52882026899361
                    ],
                    [
                        119.55378401656903,
                        23.529007000979476
                    ],
                    [
                        119.55396303188903,
                        23.52914858393151
                    ],
                    [
                        119.55403836059293,
                        23.52923184193281
                    ],
                    [
                        119.55410753123238,
                        23.529306091932906
                    ],
                    [
                        119.55419559725786,
                        23.52943445396351
                    ],
                    [
                        119.5542431159559,
                        23.529526840000898
                    ],
                    [
                        119.55432487916083,
                        23.52968457106565
                    ],
                    [
                        119.55437892548521,
                        23.52987400618479
                    ],
                    [
                        119.55437663459419,
                        23.530056868348428
                    ],
                    [
                        119.55431205269674,
                        23.53027381559508
                    ],
                    [
                        119.55430356979116,
                        23.530294162620212
                    ],
                    [
                        119.55477077013198,
                        23.530409885328694
                    ],
                    [
                        119.55489232378117,
                        23.530131783970226
                    ],
                    [
                        119.55494602724953,
                        23.530020976821536
                    ],
                    [
                        119.5549376245413,
                        23.52991490573077
                    ],
                    [
                        119.5548833717761,
                        23.529822543693363
                    ],
                    [
                        119.55482897525982,
                        23.529768558691934
                    ],
                    [
                        119.55475541285848,
                        23.52974173173287
                    ],
                    [
                        119.55473957646763,
                        23.529687608697657
                    ],
                    [
                        119.5547355439143,
                        23.529601839623243
                    ],
                    [
                        119.55475448245856,
                        23.529520503532133
                    ],
                    [
                        119.55478878914653,
                        23.529454913441086
                    ],
                    [
                        119.55476914954602,
                        23.529369200380795
                    ],
                    [
                        119.55476121309515,
                        23.52930150432643
                    ],
                    [
                        119.55482264368341,
                        23.52920873018473
                    ],
                    [
                        119.55503807137606,
                        23.528912233708557
                    ],
                    [
                        119.55535354572076,
                        23.528536368050048
                    ],
                    [
                        119.55561492342638,
                        23.528250995516885
                    ],
                    [
                        119.55596158807207,
                        23.527942741863164
                    ],
                    [
                        119.55633966600067,
                        23.527681781209814
                    ],
                    [
                        119.55659418078778,
                        23.527583799842976
                    ],
                    [
                        119.55690708855369,
                        23.527472063396395
                    ],
                    [
                        119.5570033735264,
                        23.52744463026544
                    ],
                    [
                        119.55716910903432,
                        23.527340193976933
                    ],
                    [
                        119.55723033506584,
                        23.527200011759003
                    ],
                    [
                        119.5572680656145,
                        23.52700347750364
                    ],
                    [
                        119.55733326061545,
                        23.526861022276293
                    ],
                    [
                        119.55736013398973,
                        23.52677514315231
                    ],
                    [
                        119.55744866371273,
                        23.526722903996717
                    ],
                    [
                        119.55775775257668,
                        23.526649557571343
                    ],
                    [
                        119.55792779861152,
                        23.526624115352874
                    ],
                    [
                        119.55812705134821,
                        23.52655793405413
                    ],
                    [
                        119.55824972943734,
                        23.526548464905648
                    ],
                    [
                        119.55827923312128,
                        23.52650546682241
                    ],
                    [
                        119.55830875584154,
                        23.526466983744275
                    ],
                    [
                        119.55840165344077,
                        23.52643504663211
                    ],
                    [
                        119.55861779298222,
                        23.526454587520913
                    ],
                    [
                        119.559087570677,
                        23.526459672236165
                    ],
                    [
                        119.55959123909136,
                        23.526446574898813
                    ],
                    [
                        119.55977340977736,
                        23.526466236823612
                    ],
                    [
                        119.56010790483222,
                        23.526467290619582
                    ],
                    [
                        119.56039043320109,
                        23.526482075480306
                    ],
                    [
                        119.56056104215375,
                        23.526517580463526
                    ],
                    [
                        119.56076018927779,
                        23.526571042483575
                    ],
                    [
                        119.56098500619692,
                        23.52668762167219
                    ],
                    [
                        119.56113775389488,
                        23.526768338821775
                    ],
                    [
                        119.5613291979689,
                        23.526952761269754
                    ],
                    [
                        119.56140602583598,
                        23.527099220673477
                    ],
                    [
                        119.56139802568548,
                        23.527232440065703
                    ],
                    [
                        119.5613435958698,
                        23.527386144520644
                    ],
                    [
                        119.56123026462596,
                        23.527506198870565
                    ],
                    [
                        119.56111189088847,
                        23.52759240911113
                    ],
                    [
                        119.56088805354105,
                        23.527706089403864
                    ],
                    [
                        119.56074892789049,
                        23.527805919645527
                    ],
                    [
                        119.56073200152423,
                        23.52785564476954
                    ],
                    [
                        119.56079173758808,
                        23.527941213001238
                    ],
                    [
                        119.56077089942238,
                        23.528006755164686
                    ],
                    [
                        119.56070741894179,
                        23.528047618251104
                    ],
                    [
                        119.56047518194555,
                        23.52812972238012
                    ],
                    [
                        119.56006936951266,
                        23.528271146548313
                    ],
                    [
                        119.55979038550478,
                        23.528371478631925
                    ],
                    [
                        119.5608628055904,
                        23.53082826158465
                    ],
                    [
                        119.56102336102069,
                        23.530800593813193
                    ],
                    [
                        119.56115576933006,
                        23.530775283990963
                    ],
                    [
                        119.56126907913932,
                        23.530720697046036
                    ],
                    [
                        119.56139196225023,
                        23.530686392170473
                    ],
                    [
                        119.56146747634902,
                        23.530668060252715
                    ],
                    [
                        119.56158083426558,
                        23.530624760325335
                    ],
                    [
                        119.56169422929398,
                        23.53059048842037
                    ],
                    [
                        119.56176962897806,
                        23.530545067409964
                    ],
                    [
                        119.56189251101966,
                        23.5305107625121
                    ],
                    [
                        119.56203431995823,
                        23.530465101604072
                    ],
                    [
                        119.56213808337493,
                        23.530397003550203
                    ],
                    [
                        119.56224209766445,
                        23.53038759768905
                    ],
                    [
                        119.56232728831614,
                        23.53034214167117
                    ],
                    [
                        119.56244068424132,
                        23.530307869732987
                    ],
                    [
                        119.56256328929598,
                        23.53028033782913
                    ],
                    [
                        119.56264848994145,
                        23.530237137805912
                    ],
                    [
                        119.56279000178458,
                        23.53019373486361
                    ],
                    [
                        119.56290921557132,
                        23.529303858666083
                    ],
                    [
                        119.56307552745959,
                        23.52933486195561
                    ],
                    [
                        119.56370274603366,
                        23.529510933352366
                    ],
                    [
                        119.56403218078228,
                        23.529613584182066
                    ],
                    [
                        119.56434438921544,
                        23.529695980935493
                    ],
                    [
                        119.56453808603581,
                        23.529760744482374
                    ],
                    [
                        119.56463509469219,
                        23.529830375939785
                    ],
                    [
                        119.56478636438275,
                        23.529992365929207
                    ],
                    [
                        119.56483323215996,
                        23.530073465393055
                    ],
                    [
                        119.56483719652338,
                        23.53014117573101
                    ],
                    [
                        119.56479784396313,
                        23.530170665816133
                    ],
                    [
                        119.56474773113531,
                        23.53018890682884
                    ],
                    [
                        119.56471911069639,
                        23.530222872949604
                    ],
                    [
                        119.56471608324246,
                        23.530301894327124
                    ],
                    [
                        119.56477714119804,
                        23.530337794599042
                    ],
                    [
                        119.56495647432273,
                        23.53040712523254
                    ],
                    [
                        119.5650610240932,
                        23.530521876982775
                    ],
                    [
                        119.56517248533528,
                        23.53060725760935
                    ],
                    [
                        119.56534490817528,
                        23.53070596042665
                    ],
                    [
                        119.56550327862946,
                        23.53088146964341
                    ],
                    [
                        119.56574416859095,
                        23.531101828302468
                    ],
                    [
                        119.56591675852405,
                        23.531238907413723
                    ],
                    [
                        119.56603244990337,
                        23.531452948857133
                    ],
                    [
                        119.56608330460861,
                        23.53160627283368
                    ],
                    [
                        119.56604793663199,
                        23.531707987320818
                    ],
                    [
                        119.565908758189,
                        23.531866516862575
                    ],
                    [
                        119.56574835498297,
                        23.532000290189835
                    ],
                    [
                        119.56560571087606,
                        23.532136257551112
                    ],
                    [
                        119.56552014136076,
                        23.532235896852907
                    ],
                    [
                        119.56546356412711,
                        23.532387352497732
                    ],
                    [
                        119.56542093735753,
                        23.532509412018705
                    ],
                    [
                        119.56532903913053,
                        23.532773870128334
                    ],
                    [
                        119.56525442472842,
                        23.532929906706666
                    ],
                    [
                        119.56521891886486,
                        23.533000016956013
                    ],
                    [
                        119.5651224803132,
                        23.53306357597549
                    ],
                    [
                        119.56492575529293,
                        23.53315007377925
                    ],
                    [
                        119.5647433952544,
                        23.53323200358841
                    ],
                    [
                        119.5645396530274,
                        23.53339527828883
                    ],
                    [
                        119.56447910512648,
                        23.533479022956914
                    ],
                    [
                        119.56443999941474,
                        23.533567205689494
                    ],
                    [
                        119.56443340294346,
                        23.533671071505978
                    ],
                    [
                        119.56447692099813,
                        23.53375669751758
                    ],
                    [
                        119.56454946705938,
                        23.53390316953122
                    ],
                    [
                        119.5646283515393,
                        23.533957062709952
                    ],
                    [
                        119.56475798621014,
                        23.53406946496634
                    ],
                    [
                        119.56484753581006,
                        23.534112032198028
                    ],
                    [
                        119.5648801878789,
                        23.534161577229572
                    ],
                    [
                        119.56489115071815,
                        23.534220232174746
                    ],
                    [
                        119.56495942995821,
                        23.534298994279226
                    ],
                    [
                        119.56501748691008,
                        23.534420686282807
                    ],
                    [
                        119.56508578510882,
                        23.534503964380203
                    ],
                    [
                        119.56513968851901,
                        23.534512799545777
                    ],
                    [
                        119.565211179254,
                        23.534483193829686
                    ],
                    [
                        119.56525768965534,
                        23.534480766988207
                    ],
                    [
                        119.56532226619802,
                        23.534480533203293
                    ],
                    [
                        119.565462681399,
                        23.5346809363579
                    ],
                    [
                        119.56553104682752,
                        23.53470777854336
                    ],
                    [
                        119.56561693166748,
                        23.534680377871656
                    ]
                ]
            ]
        ]
    },
    "startTime": "11:00:00",
    "lastUpdatedTime": "2025-06-25T02:18:12.540+0000",
    "endTime": "16:00:00",
    "category": 1,
    "type": 1,
    "startDate": "2025-06-24T16:00:00.000+0000",
    "pressureDownArea": null,
    "isSchedule": false
}