{
    "no": "202509120007",
    "endDate": "2025-09-11T16:00:00.000+0000",
    "actualEndTime": null,
    "waterOffArea": {
        "type": "MultiPolygon",
        "coordinates": [
            [
                [
                    [
                        120.36685466766359,
                        23.499513040154728
                    ],
                    [
                        120.36720871925355,
                        23.498725915919547
                    ],
                    [
                        120.36898970603944,
                        23.498450421326492
                    ],
                    [
                        120.36957979202273,
                        23.49850453638131
                    ],
                    [
                        120.37172555923463,
                        23.496241524214938
                    ],
                    [
                        120.37155389785767,
                        23.4934077846234
                    ],
                    [
                        120.37155389785767,
                        23.49082981582473
                    ],
                    [
                        120.35835742950441,
                        23.491380836292848
                    ],
                    [
                        120.35726308822633,
                        23.50161365494
                    ],
                    [
                        120.3660821914673,
                        23.501633332671943
                    ],
                    [
                        120.36685466766359,
                        23.499513040154728
                    ]
                ]
            ]
        ]
    },
    "startTime": "09:00:00",
    "lastUpdatedTime": "2025-09-12T00:33:56.040+0000",
    "endTime": "17:00:00",
    "category": 1,
    "type": 1,
    "startDate": "2025-09-11T16:00:00.000+0000",
    "pressureDownArea": null,
    "isSchedule": false
}