{
    "no": "202510130064",
    "endDate": "2025-10-12T16:00:00.000+0000",
    "actualEndTime": null,
    "waterOffArea": {
        "type": "MultiPolygon",
        "coordinates": [
            [
                [
                    [
                        121.05858296155931,
                        24.700878236075795
                    ],
                    [
                        121.0579338669777,
                        24.701012259544097
                    ],
                    [
                        121.0577219724655,
                        24.70108292640568
                    ],
                    [
                        121.05790436267853,
                        24.701324168148393
                    ],
                    [
                        121.05857223272322,
                        24.701870006326548
                    ],
                    [
                        121.05876803398131,
                        24.702352486296
                    ],
                    [
                        121.0590550303459,
                        24.702440209726014
                    ],
                    [
                        121.0593581199646,
                        24.701721363131092
                    ],
                    [
                        121.05859100818634,
                        24.700848994572638
                    ],
                    [
                        121.05858296155931,
                        24.700878236075795
                    ]
                ]
            ],
            [
                [
                    [
                        121.05858027935027,
                        24.700880672867406
                    ],
                    [
                        121.05849981307982,
                        24.700912351154134
                    ],
                    [
                        121.05849981307982,
                        24.700912351154134
                    ],
                    [
                        121.05845153331758,
                        24.700902603989846
                    ],
                    [
                        121.05858027935027,
                        24.700880672867406
                    ]
                ]
            ]
        ]
    },
    "startTime": "12:30:00",
    "lastUpdatedTime": "2025-10-13T04:10:19.762+0000",
    "endTime": "17:00:00",
    "category": 1,
    "type": 1,
    "startDate": "2025-10-12T16:00:00.000+0000",
    "pressureDownArea": null,
    "isSchedule": false
}