{
    "no": "202503260017",
    "endDate": "2025-03-26T16:00:00.000+0000",
    "actualEndTime": null,
    "waterOffArea": null,
    "startTime": "08:30:00",
    "lastUpdatedTime": "2025-03-26T02:04:41.167+0000",
    "endTime": "14:00:00",
    "category": 1,
    "type": 2,
    "startDate": "2025-03-26T16:00:00.000+0000",
    "pressureDownArea": {
        "type": "MultiPolygon",
        "coordinates": [
            [
                [
                    [
                        120.52521064993141,
                        22.886664082221987
                    ],
                    [
                        120.52521064993141,
                        22.886358569391145
                    ],
                    [
                        120.52431333052606,
                        22.885873342426727
                    ],
                    [
                        120.52419628772566,
                        22.8815601350713
                    ],
                    [
                        120.51865630680491,
                        22.880140341149918
                    ],
                    [
                        120.51658856725348,
                        22.877624214430703
                    ],
                    [
                        120.51307731205392,
                        22.87864864314837
                    ],
                    [
                        120.50925394490272,
                        22.87787582847682
                    ],
                    [
                        120.5059377601641,
                        22.87766015932298
                    ],
                    [
                        120.50324579736422,
                        22.880517755653507
                    ],
                    [
                        120.5056646620427,
                        22.88510056948477
                    ],
                    [
                        120.5152425868358,
                        22.886268712900204
                    ],
                    [
                        120.52521064993141,
                        22.886664082221987
                    ]
                ]
            ]
        ]
    },
    "isSchedule": false
}