{
    "no": "202507050011",
    "endDate": "2025-07-04T16:00:00.000+0000",
    "actualEndTime": "2025-07-05T03:33:35.120+0000",
    "waterOffArea": null,
    "startTime": "09:03:00",
    "lastUpdatedTime": "2025-07-05T03:33:35.120+0000",
    "endTime": "20:00:00",
    "category": 1,
    "type": 1,
    "startDate": "2025-07-04T16:00:00.000+0000",
    "pressureDownArea": {
        "type": "MultiPolygon",
        "coordinates": [
            [
                [
                    [
                        120.7266354560852,
                        24.115470494225402
                    ],
                    [
                        120.72736501693726,
                        24.11496128503323
                    ],
                    [
                        120.72858810424803,
                        24.113962445733755
                    ],
                    [
                        120.73049783706665,
                        24.11237603788521
                    ],
                    [
                        120.7310128211975,
                        24.112297696247467
                    ],
                    [
                        120.72996139526369,
                        24.11015307529427
                    ],
                    [
                        120.72893142700195,
                        24.103885483964074
                    ],
                    [
                        120.728759765625,
                        24.095697980734847
                    ],
                    [
                        120.729660987854,
                        24.09162362145771
                    ],
                    [
                        120.73099136352539,
                        24.088685301189553
                    ],
                    [
                        120.73519706726076,
                        24.0883326982299
                    ],
                    [
                        120.73629140853883,
                        24.086187675990654
                    ],
                    [
                        120.73710680007935,
                        24.084365848087792
                    ],
                    [
                        120.73751449584961,
                        24.08338636001745
                    ],
                    [
                        120.74187040328977,
                        24.08612890775281
                    ],
                    [
                        120.74137687683108,
                        24.09470878522407
                    ],
                    [
                        120.73605537414551,
                        24.108312002164933
                    ],
                    [
                        120.74622631072997,
                        24.120650603369278
                    ],
                    [
                        120.76352119445804,
                        24.106314212011622
                    ],
                    [
                        120.7763957977295,
                        24.098988714790398
                    ],
                    [
                        120.78742504119876,
                        24.108390346241666
                    ],
                    [
                        120.78154563903809,
                        24.10921295615306
                    ],
                    [
                        120.77390670776369,
                        24.105491583476912
                    ],
                    [
                        120.76609611511232,
                        24.10889958157193
                    ],
                    [
                        120.74416637420654,
                        24.135142044163644
                    ],
                    [
                        120.73511123657225,
                        24.131773909779984
                    ],
                    [
                        120.7266354560852,
                        24.115470494225402
                    ]
                ]
            ]
        ]
    },
    "isSchedule": false
}